qlik_test_yuri/__init__.py
qlik_test_yuri-0.1.1.dist-info/METADATA
qlik_test_yuri-0.1.1.dist-info/WHEEL
qlik_test_yuri-0.1.1.dist-info/RECORD
